verbalizer/__init__.py
verbalizer/nlp.py
verbalizer/patterns/__init__.py
verbalizer/patterns/owl_disjoint.py
verbalizer/patterns/owl_first_rest.py
verbalizer/patterns/owl_restriction.py
verbalizer/process.py
verbalizer/sampler.py
verbalizer/verbalizer.py
verbalizer/vocabulary.py
ontology_verbalizer-1.1.2.dist-info/METADATA
ontology_verbalizer-1.1.2.dist-info/WHEEL
ontology_verbalizer-1.1.2.dist-info/RECORD
