Metadata-Version: 2.3
Name: ontology-verbalizer
Version: 1.1.2
Summary: A Python package for ontology verbalization
License: MIT
Author: Antonio Zaitoun
Author-email: tony.z.1711@gmail.com
Requires-Python: >=3.12,<4.0
Classifier: License :: OSI Approved :: MIT License
Classifier: Programming Language :: Python :: 3
Classifier: Programming Language :: Python :: 3.12
Classifier: Programming Language :: Python :: 3.13
Requires-Dist: pandas (>=2.2.0,<2.3.0)
Requires-Dist: rdflib (>=7.0.0,<7.1.0)
Requires-Dist: tqdm (>=4.66.2,<4.67.0)
Project-URL: Repository, https://github.com/Minitour/ontology-verbalizer
